time_what/__init__.py
time_what/py.typed
time_what/timer.py
time_what-0.1.1.dist-info/METADATA
time_what-0.1.1.dist-info/WHEEL
time_what-0.1.1.dist-info/RECORD
