Metadata-Version: 2.1
Name: time-what
Version: 0.1.1
Summary: 
Author: Marc
Requires-Python: >=3.12,<4.0
Classifier: Programming Language :: Python :: 3
Classifier: Programming Language :: Python :: 3.12
